vinson/VinsonDB.py
vinson/__init__.py
vinson-0.1.dist-info/LICENSE
vinson-0.1.dist-info/METADATA
vinson-0.1.dist-info/WHEEL
vinson-0.1.dist-info/top_level.txt
vinson-0.1.dist-info/RECORD
