Metadata-Version: 2.1
Name: vinson
Version: 0.1
Summary: Vinson Database is a lightweight, file-based Python database.
Author-email: Vinayak Mahajan <vinayakmahajan06@gmail.com>
Project-URL: Homepage, https://github.com/vinmahajan/vinson
Project-URL: Issues, https://github.com/vinmahajan/vinson/issues
Classifier: Programming Language :: Python :: 3
Classifier: License :: OSI Approved :: MIT License
Classifier: Operating System :: OS Independent
Requires-Python: >=3.8
License-File: LICENSE
